throttle_cli/__init__.py
throttle_cli/arglib.py
throttle_cli/cli_client.py
throttle_cli/cli_server.py
throttle_cli/client.py
throttle_cli/commandworker.py
throttle_cli/infoparser.py
throttle_cli/loglib.py
throttle_cli/server.py
throttle_cli/structures.py
throttle_cli-0.3.0.dist-info/LICENSE
throttle_cli-0.3.0.dist-info/METADATA
throttle_cli-0.3.0.dist-info/WHEEL
throttle_cli-0.3.0.dist-info/entry_points.txt
throttle_cli-0.3.0.dist-info/RECORD
