Metadata-Version: 2.1
Name: throttle-cli
Version: 0.3.0
Summary: Throttle commands triggered from multiple async sources.
Home-page: https://sr.ht/~ferdinandyb/throttle/
License: EUPL-1.2
Author: Bence Ferdinandy
Author-email: bence@ferdinandy.com
Requires-Python: >=3.10
Classifier: License :: OSI Approved :: European Union Public Licence 1.2 (EUPL 1.2)
Classifier: Programming Language :: Python :: 3
Classifier: Programming Language :: Python :: 3.10
Classifier: Programming Language :: Python :: 3.11
Classifier: Programming Language :: Python :: 3.12
Requires-Dist: jsonrpclib-pelix (>=0.4.3.2,<0.5.0.0)
Requires-Dist: prettytable (>=3.10.0,<4.0.0)
Requires-Dist: pyxdg (>=0.28,<0.29)
Requires-Dist: toml (>=0.10.2,<0.11.0)
